{
  "protocol_version" : "0.0.6",
  "configuration" : {
    "version" : "(6.12.0.140) (2020-02/51d876a041e)",
    "tlc" : "normal",
    "sigsgev" : "altstack",
    "notifications" : "kqueue",
    "architecture" : "amd64",
    "disabled_features" : "none",
    "smallconfig" : "disabled",
    "bigarrays" : "disabled",
    "softdebug" : "enabled",
    "interpreter" : "enabled",
    "llvm_support" : "0",
    "suspend" : "hybrid"
  },
  "memory" : {
    "Resident Size" : "185147392",
    "Virtual Size" : "4869259264",
    "minor_gc_time" : "223342",
    "major_gc_time" : "0",
    "minor_gc_count" : "1",
    "major_gc_count" : "0",
    "major_gc_time_concurrent" : "0"
 },
  "threads" : [
 {
    "is_managed" : false,
    "offset_free_hash" : "0xb38e38d3",
    "offset_rich_hash" : "0xb38e38d3",
    "crashed" : false,
    "native_thread_id" : "0x70000c243000",
    "thread_info_addr" : "0x7f8c53830600",
    "thread_name" : "Finalizer",
    "ctx" : {
      "IP" : "0x7fff20506eba",
      "SP" : "0x70000c242eb8",
      "BP" : "0x70000c242f00"
  },
    "unmanaged_frames" : [
  {
      "is_managed" : "false",
      "native_address" : "0x103f5c956",
      "native_offset" : "0x00000"
   }
,
  {
      "is_managed" : "false",
      "native_address" : "0x1040f80d5",
      "native_offset" : "0x00000"
   }
,
  {
      "is_managed" : "false",
      "native_address" : "0x1040f7e07",
      "native_offset" : "0x00000"
   }
,
  {
      "is_managed" : "false",
      "native_address" : "0x103fc8920",
      "native_offset" : "0x00000"
   }
,
  {
      "is_managed" : "false",
      "native_address" : "0x7fff2057fd7d",
      "native_offset" : "0x00000"
   }
,
  {
      "is_managed" : "true",
      "guid" : "92218043-4747-44EA-9D64-D27064C35DCB",
      "token" : "0x600146e",
      "native_offset" : "0x0",
      "filename" : "mscorlib.dll",
      "sizeofimage" : "0x472000",
      "timestamp" : "0xa45d0dbd",
      "il_offset" : "0x00000"
   }
,
  {
      "is_managed" : "false",
      "native_address" : "0x1040f8d1d",
      "native_offset" : "0x00000"
   }
,
  {
      "is_managed" : "false",
      "native_address" : "0x7fff2053b950",
      "native_offset" : "0x00000"
   }
,
  {
      "is_managed" : "false",
      "native_address" : "0x7fff2053747b",
      "native_offset" : "0x00000"
   }

  ]
 },
 {
    "is_managed" : true,
    "offset_free_hash" : "0x11a67480d0",
    "offset_rich_hash" : "0x11a67485e5",
    "crashed" : true,
    "native_thread_id" : "0x70000f5d7000",
    "thread_info_addr" : "0x7f8c54b0b800",
    "thread_name" : "tid_7103",
    "ctx" : {
      "IP" : "0x7fff2050d462",
      "SP" : "0x70000f5cfb48",
      "BP" : "0x70000f5cfb70"
  },
    "managed_frames" : [
  {
      "is_managed" : "false",
      "native_address" : "unregistered"
   }
,
  {
      "is_managed" : "true",
      "guid" : "92218043-4747-44EA-9D64-D27064C35DCB",
      "token" : "0x00000",
      "native_offset" : "0x0",
      "filename" : "mscorlib.dll",
      "sizeofimage" : "0x472000",
      "timestamp" : "0xa45d0dbd",
      "il_offset" : "0x00000"
   }
,
  {
      "is_managed" : "true",
      "guid" : "92218043-4747-44EA-9D64-D27064C35DCB",
      "token" : "0x00000",
      "native_offset" : "0x0",
      "filename" : "mscorlib.dll",
      "sizeofimage" : "0x472000",
      "timestamp" : "0xa45d0dbd",
      "il_offset" : "0x00015"
   }
,
  {
      "is_managed" : "true",
      "guid" : "BD24F2D5-173E-4EF0-BCAC-9E2F08461AE4",
      "token" : "0x600427f",
      "native_offset" : "0x0",
      "filename" : "System.dll",
      "sizeofimage" : "0x290000",
      "timestamp" : "0xae21f1c6",
      "il_offset" : "0x0026a"
   }
,
  {
      "is_managed" : "true",
      "guid" : "BD24F2D5-173E-4EF0-BCAC-9E2F08461AE4",
      "token" : "0x600447f",
      "native_offset" : "0x0",
      "filename" : "System.dll",
      "sizeofimage" : "0x290000",
      "timestamp" : "0xae21f1c6",
      "il_offset" : "0x00043"
   }
,
  {
      "is_managed" : "true",
      "guid" : "92218043-4747-44EA-9D64-D27064C35DCB",
      "token" : "0x6001ed3",
      "native_offset" : "0x0",
      "filename" : "mscorlib.dll",
      "sizeofimage" : "0x472000",
      "timestamp" : "0xa45d0dbd",
      "il_offset" : "0x00071"
   }
,
  {
      "is_managed" : "true",
      "guid" : "92218043-4747-44EA-9D64-D27064C35DCB",
      "token" : "0x6001ed1",
      "native_offset" : "0x0",
      "filename" : "mscorlib.dll",
      "sizeofimage" : "0x472000",
      "timestamp" : "0xa45d0dbd",
      "il_offset" : "0x00000"
   }
,
  {
      "is_managed" : "true",
      "guid" : "92218043-4747-44EA-9D64-D27064C35DCB",
      "token" : "0x6001ed0",
      "native_offset" : "0x0",
      "filename" : "mscorlib.dll",
      "sizeofimage" : "0x472000",
      "timestamp" : "0xa45d0dbd",
      "il_offset" : "0x0002b"
   }
,
  {
      "is_managed" : "true",
      "guid" : "BD24F2D5-173E-4EF0-BCAC-9E2F08461AE4",
      "token" : "0x600427e",
      "native_offset" : "0x0",
      "filename" : "System.dll",
      "sizeofimage" : "0x290000",
      "timestamp" : "0xae21f1c6",
      "il_offset" : "0x00093"
   }
,
  {
      "is_managed" : "true",
      "guid" : "BD24F2D5-173E-4EF0-BCAC-9E2F08461AE4",
      "token" : "0x00000",
      "native_offset" : "0x0",
      "filename" : "System.dll",
      "sizeofimage" : "0x290000",
      "timestamp" : "0xae21f1c6",
      "il_offset" : "0xffffffff"
   }
,
  {
      "is_managed" : "false",
      "native_address" : "unregistered"
   }
,
  {
      "is_managed" : "true",
      "guid" : "BD24F2D5-173E-4EF0-BCAC-9E2F08461AE4",
      "token" : "0x00000",
      "native_offset" : "0x0",
      "filename" : "System.dll",
      "sizeofimage" : "0x290000",
      "timestamp" : "0xae21f1c6",
      "il_offset" : "0x00000"
   }
,
  {
      "is_managed" : "true",
      "guid" : "BD24F2D5-173E-4EF0-BCAC-9E2F08461AE4",
      "token" : "0x6004477",
      "native_offset" : "0x0",
      "filename" : "System.dll",
      "sizeofimage" : "0x290000",
      "timestamp" : "0xae21f1c6",
      "il_offset" : "0x0003a"
   }
,
  {
      "is_managed" : "true",
      "guid" : "92218043-4747-44EA-9D64-D27064C35DCB",
      "token" : "0x6001f2b",
      "native_offset" : "0x0",
      "filename" : "mscorlib.dll",
      "sizeofimage" : "0x472000",
      "timestamp" : "0xa45d0dbd",
      "il_offset" : "0x00025"
   }
,
  {
      "is_managed" : "true",
      "guid" : "92218043-4747-44EA-9D64-D27064C35DCB",
      "token" : "0x6001ed3",
      "native_offset" : "0x0",
      "filename" : "mscorlib.dll",
      "sizeofimage" : "0x472000",
      "timestamp" : "0xa45d0dbd",
      "il_offset" : "0x00071"
   }
,
  {
      "is_managed" : "true",
      "guid" : "92218043-4747-44EA-9D64-D27064C35DCB",
      "token" : "0x6001ed1",
      "native_offset" : "0x0",
      "filename" : "mscorlib.dll",
      "sizeofimage" : "0x472000",
      "timestamp" : "0xa45d0dbd",
      "il_offset" : "0x00000"
   }
,
  {
      "is_managed" : "true",
      "guid" : "92218043-4747-44EA-9D64-D27064C35DCB",
      "token" : "0x6001ed0",
      "native_offset" : "0x0",
      "filename" : "mscorlib.dll",
      "sizeofimage" : "0x472000",
      "timestamp" : "0xa45d0dbd",
      "il_offset" : "0x0002b"
   }
,
  {
      "is_managed" : "true",
      "guid" : "92218043-4747-44EA-9D64-D27064C35DCB",
      "token" : "0x00000",
      "native_offset" : "0x0",
      "filename" : "mscorlib.dll",
      "sizeofimage" : "0x472000",
      "timestamp" : "0xa45d0dbd",
      "il_offset" : "0x0002a"
   }

  ],
  "unmanaged_frames" : [
 {
    "is_managed" : "false",
    "native_address" : "0x103f5c956",
    "native_offset" : "0x00000"
  }
,
 {
    "is_managed" : "false",
    "native_address" : "0x1040f80d5",
    "native_offset" : "0x00000"
  }
,
 {
    "is_managed" : "false",
    "native_address" : "0x1040f874a",
    "native_offset" : "0x00000"
  }
,
 {
    "is_managed" : "false",
    "native_address" : "0x103fc99e7",
    "native_offset" : "0x00000"
  }
,
 {
    "is_managed" : "false",
    "native_address" : "0x103f615ee",
    "native_offset" : "0x00000"
  }
,
 {
    "is_managed" : "false",
    "native_address" : "0x103fc8cdf",
    "native_offset" : "0x00000"
  }
,
 {
    "is_managed" : "false",
    "native_address" : "0x7fff2057fd7d",
    "native_offset" : "0x00000"
  }
,
 {
    "is_managed" : "false",
    "native_address" : "unregistered"
  }
,
 {
    "is_managed" : "false",
    "native_address" : "0x7fff2048e720",
    "native_offset" : "0x00000"
  }
,
 {
    "is_managed" : "false",
    "native_address" : "0x1041b5f57",
    "native_offset" : "0x00000"
  }
,
 {
    "is_managed" : "false",
    "native_address" : "0x104196dbf",
    "native_offset" : "0x00000"
  }
,
 {
    "is_managed" : "false",
    "native_address" : "0x1041b63ee",
    "native_offset" : "0x00000"
  }
,
 {
    "is_managed" : "false",
    "native_address" : "0x1041b656f",
    "native_offset" : "0x00000"
  }
,
 {
    "is_managed" : "false",
    "native_address" : "0x1041b65aa",
    "native_offset" : "0x00000"
  }
,
 {
    "is_managed" : "false",
    "native_address" : "0x1041aad7e",
    "native_offset" : "0x00000"
  }
,
 {
    "is_managed" : "false",
    "native_address" : "0x1040f2641",
    "native_offset" : "0x00000"
  }
,
 {
    "is_managed" : "false",
    "native_address" : "0x1040f92bd",
    "native_offset" : "0x00000"
  }
,
 {
    "is_managed" : "false",
    "native_address" : "0x1040f6f2c",
    "native_offset" : "0x00000"
  }
,
 {
    "is_managed" : "true",
    "guid" : "92218043-4747-44EA-9D64-D27064C35DCB",
    "token" : "0x00000",
    "native_offset" : "0x0",
    "filename" : "mscorlib.dll",
    "sizeofimage" : "0x472000",
    "timestamp" : "0xa45d0dbd",
    "il_offset" : "0x00000"
  }
,
 {
    "is_managed" : "true",
    "guid" : "92218043-4747-44EA-9D64-D27064C35DCB",
    "token" : "0x00000",
    "native_offset" : "0x0",
    "filename" : "mscorlib.dll",
    "sizeofimage" : "0x472000",
    "timestamp" : "0xa45d0dbd",
    "il_offset" : "0x00000"
  }
,
 {
    "is_managed" : "true",
    "guid" : "BD24F2D5-173E-4EF0-BCAC-9E2F08461AE4",
    "token" : "0x600427f",
    "native_offset" : "0x0",
    "filename" : "System.dll",
    "sizeofimage" : "0x290000",
    "timestamp" : "0xae21f1c6",
    "il_offset" : "0x00000"
  }
,
 {
    "is_managed" : "true",
    "guid" : "BD24F2D5-173E-4EF0-BCAC-9E2F08461AE4",
    "token" : "0x600447f",
    "native_offset" : "0x0",
    "filename" : "System.dll",
    "sizeofimage" : "0x290000",
    "timestamp" : "0xae21f1c6",
    "il_offset" : "0x00000"
  }
,
 {
    "is_managed" : "true",
    "guid" : "92218043-4747-44EA-9D64-D27064C35DCB",
    "token" : "0x6001ed3",
    "native_offset" : "0x0",
    "filename" : "mscorlib.dll",
    "sizeofimage" : "0x472000",
    "timestamp" : "0xa45d0dbd",
    "il_offset" : "0x00000"
  }
,
 {
    "is_managed" : "true",
    "guid" : "92218043-4747-44EA-9D64-D27064C35DCB",
    "token" : "0x6001ed1",
    "native_offset" : "0x0",
    "filename" : "mscorlib.dll",
    "sizeofimage" : "0x472000",
    "timestamp" : "0xa45d0dbd",
    "il_offset" : "0x00000"
  }
,
 {
    "is_managed" : "true",
    "guid" : "BD24F2D5-173E-4EF0-BCAC-9E2F08461AE4",
    "token" : "0x00000",
    "native_offset" : "0x0",
    "filename" : "System.dll",
    "sizeofimage" : "0x290000",
    "timestamp" : "0xae21f1c6",
    "il_offset" : "0x00000"
  }
,
 {
    "is_managed" : "false",
    "native_address" : "0x7fff27346957",
    "native_offset" : "0x00000"
  }
,
 {
    "is_managed" : "false",
    "native_address" : "0x7fff27345d7e",
    "native_offset" : "0x00000"
  }
,
 {
    "is_managed" : "false",
    "native_address" : "0x7fff27345c77",
    "native_offset" : "0x00000"
  }
,
 {
    "is_managed" : "false",
    "native_address" : "0x7fff273488bf",
    "native_offset" : "0x00000"
  }
,
 {
    "is_managed" : "false",
    "native_address" : "0x7fff20660684",
    "native_offset" : "0x00000"
  }
,
 {
    "is_managed" : "false",
    "native_address" : "0x7fff20634188",
    "native_offset" : "0x00000"
  }
,
 {
    "is_managed" : "false",
    "native_address" : "0x7fff20634065",
    "native_offset" : "0x00000"
  }
,
 {
    "is_managed" : "false",
    "native_address" : "0x7fff20632709",
    "native_offset" : "0x00000"
  }
,
 {
    "is_managed" : "false",
    "native_address" : "0x7fff206316ce",
    "native_offset" : "0x00000"
  }
,
 {
    "is_managed" : "false",
    "native_address" : "0x7fff206b7cc9",
    "native_offset" : "0x00000"
  }
,
 {
    "is_managed" : "false",
    "native_address" : "0x106f6efcc",
    "native_offset" : "0x00000"
  }
,
 {
    "is_managed" : "true",
    "guid" : "BD24F2D5-173E-4EF0-BCAC-9E2F08461AE4",
    "token" : "0x00000",
    "native_offset" : "0x0",
    "filename" : "System.dll",
    "sizeofimage" : "0x290000",
    "timestamp" : "0xae21f1c6",
    "il_offset" : "0x00000"
  }
,
 {
    "is_managed" : "true",
    "guid" : "BD24F2D5-173E-4EF0-BCAC-9E2F08461AE4",
    "token" : "0x6004477",
    "native_offset" : "0x0",
    "filename" : "System.dll",
    "sizeofimage" : "0x290000",
    "timestamp" : "0xae21f1c6",
    "il_offset" : "0x00000"
  }
,
 {
    "is_managed" : "true",
    "guid" : "92218043-4747-44EA-9D64-D27064C35DCB",
    "token" : "0x6001f2b",
    "native_offset" : "0x0",
    "filename" : "mscorlib.dll",
    "sizeofimage" : "0x472000",
    "timestamp" : "0xa45d0dbd",
    "il_offset" : "0x00000"
  }
,
 {
    "is_managed" : "true",
    "guid" : "92218043-4747-44EA-9D64-D27064C35DCB",
    "token" : "0x6001ed1",
    "native_offset" : "0x0",
    "filename" : "mscorlib.dll",
    "sizeofimage" : "0x472000",
    "timestamp" : "0xa45d0dbd",
    "il_offset" : "0x00000"
  }
,
 {
    "is_managed" : "false",
    "native_address" : "0x103ebe8c2",
    "native_offset" : "0x00000"
  }
,
 {
    "is_managed" : "false",
    "native_address" : "0x1040cdf07",
    "native_offset" : "0x00000"
  }
,
 {
    "is_managed" : "false",
    "native_address" : "0x1040d47b0",
    "native_offset" : "0x00000"
  }
,
 {
    "is_managed" : "false",
    "native_address" : "0x1040f8d5d",
    "native_offset" : "0x00000"
  }
,
 {
    "is_managed" : "false",
    "native_address" : "0x7fff2053b950",
    "native_offset" : "0x00000"
  }
,
 {
    "is_managed" : "false",
    "native_address" : "0x7fff2053747b",
    "native_offset" : "0x00000"
  }

 ]
},
{
  "is_managed" : false,
  "offset_free_hash" : "0x0",
  "offset_rich_hash" : "0x0",
  "crashed" : false,
  "native_thread_id" : "0x104ee0e00",
  "thread_info_addr" : "0x7f8c52811a00",
  "thread_name" : "tid_307",
  "ctx" : {
    "IP" : "0x7fff205098e2",
    "SP" : "0x7ffeebd53bd8",
    "BP" : "0x7ffeebd53c80"
 },
  "unmanaged_frames" : [
 {
    "is_managed" : "false",
    "native_address" : "0x103f5c956",
    "native_offset" : "0x00000"
  }
,
 {
    "is_managed" : "false",
    "native_address" : "0x1040f80d5",
    "native_offset" : "0x00000"
  }
,
 {
    "is_managed" : "false",
    "native_address" : "0x1040f7e07",
    "native_offset" : "0x00000"
  }
,
 {
    "is_managed" : "false",
    "native_address" : "0x103fc8920",
    "native_offset" : "0x00000"
  }
,
 {
    "is_managed" : "false",
    "native_address" : "0x7fff2057fd7d",
    "native_offset" : "0x00000"
  }
,
 {
    "is_managed" : "false",
    "native_address" : "0x7ffeebd53a60",
    "native_offset" : "0x00000"
  }
,
 {
    "is_managed" : "false",
    "native_address" : "0x104192e80",
    "native_offset" : "0x00000"
  }
,
 {
    "is_managed" : "false",
    "native_address" : "0x1041aafb1",
    "native_offset" : "0x00000"
  }
,
 {
    "is_managed" : "false",
    "native_address" : "0x1040f4ff4",
    "native_offset" : "0x00000"
  }
,
 {
    "is_managed" : "false",
    "native_address" : "0x1040f4dfa",
    "native_offset" : "0x00000"
  }
,
 {
    "is_managed" : "false",
    "native_address" : "0x103f21fea",
    "native_offset" : "0x00000"
  }
,
 {
    "is_managed" : "false",
    "native_address" : "0x103eae1a8",
    "native_offset" : "0x00000"
  }
,
 {
    "is_managed" : "false",
    "native_address" : "0x7fff20556621",
    "native_offset" : "0x00000"
  }

 ]
}
]
}